bemserver_api_client/__init__.py
bemserver_api_client/authentication.py
bemserver_api_client/client.py
bemserver_api_client/enums.py
bemserver_api_client/exceptions.py
bemserver_api_client/request.py
bemserver_api_client/response.py
bemserver_api_client/resources/__init__.py
bemserver_api_client/resources/about.py
bemserver_api_client/resources/analysis.py
bemserver_api_client/resources/auth.py
bemserver_api_client/resources/base.py
bemserver_api_client/resources/campaigns.py
bemserver_api_client/resources/energy.py
bemserver_api_client/resources/events.py
bemserver_api_client/resources/io.py
bemserver_api_client/resources/notifications.py
bemserver_api_client/resources/structural_elements.py
bemserver_api_client/resources/tasks.py
bemserver_api_client/resources/timeseries.py
bemserver_api_client/resources/users.py
bemserver_api_client/resources/weather.py
bemserver_api_client-0.22.0.dist-info/licenses/LICENSE
bemserver_api_client-0.22.0.dist-info/WHEEL
bemserver_api_client-0.22.0.dist-info/METADATA
bemserver_api_client-0.22.0.dist-info/RECORD
