Metadata-Version: 2.4
Name: bemserver-api-client
Version: 0.22.0
Summary: BEMServer API client
Author-email: Jérôme Lafréchoux <jlafrechoux@nobatek.inef4.com>, David Frédérique <dfrederique@nobatek.inef4.com>
Maintainer-email: Jérôme Lafréchoux <jlafrechoux@nobatek.inef4.com>, David Frédérique <dfrederique@nobatek.inef4.com>
Requires-Python: >=3.9
Classifier: Development Status :: 4 - Beta
Classifier: Intended Audience :: Developers
Classifier: Topic :: Scientific/Engineering
Classifier: License :: OSI Approved :: MIT License
Classifier: Programming Language :: Python :: 3 :: Only
Classifier: Programming Language :: Python :: 3.9
Classifier: Programming Language :: Python :: 3.10
Classifier: Programming Language :: Python :: 3.11
Classifier: Programming Language :: Python :: 3.12
License-File: LICENSE
Requires-Dist: requests>=2.32.3,<3.0.0
Project-URL: Issues, https://github.com/bemserver/bemserver-api-client/issues
Project-URL: Source, https://github.com/bemserver/bemserver-api-client
